{
    "/cars/": {
        "title": "Автомобили⭐BELGEE⭐в началии в Пензе. Цены и комплектации на новые авто в автосалоне официального дилера Белджи🔥",
        "description": "Автомобили Белджи в наличии купить в Пензе🔥Выгодный кредит🔥Выгодный трейд-ин🔥Скидки на все автомобили от розничной цены🔥Звонить по тел.: ☎ {{phone_common}}",
        "h1": "Автомобили BELGEE в наличии в Пензе"
    },
    "/contacts/": {
        "title": "Контакты официального дилера Belgee в Пензе",
        "description": "Контакты официального дилера Belgee ПАРТНЕР АВТО ПЕНЗА",
        "h1": "Контакты"
    },
    "/models/": {
        "title": "Модельный ряд автомобилей Belgee в Пензе от официального дилера",
        "description": "Модельный ряд автомобилей Belgee от официального дилера ПАРТНЕР АВТО ПЕНЗА",
        "h1": "Модельный ряд Belgee в Пензе"
    },
    "/models/s50/": {
        "title": "Купить⭐BELGEE S50⭐от {{priceb-belgee-s50}} в Пензе. Цены и комплектации на новые авто в автосалоне официального дилера Белджи🔥",
        "description": "Белджи эс 50 купить в Пензе🔥Выгодный кредит🔥Выгодный трейд-ин🔥Скидки на все автомобили от розничной цены🔥Звонить по тел.: ☎ {{phone_common}}",
        "h1": "Автомобили BELGEE S50 в Пензе"
    },
    "/models/x50/": {
        "title": "Купить⭐BELGEE X50⭐от {{priceb-belgee-x50}} в Пензе. Цены и комплектации на новые авто в автосалоне официального дилера Белджи🔥",
        "description": "Белджи икс 50 купить в Пензе🔥Выгодный кредит🔥Выгодный трейд-ин🔥Скидки на все автомобили от розничной цены🔥Звонить по тел.: ☎ {{phone_common}}",
        "h1": "Автомобили BELGEE X50 в Пензе"
    },
    "/models/x70-facelift/": {
        "title": "Купить⭐BELGEE X70 Обновленный⭐от {{priceb-belgee-x70-facelift}} в Пензе. Цены и комплектации на новые авто в автосалоне официального дилера Белджи🔥",
        "description": "Белджи икс 70 обновленный купить в Пензе🔥Выгодный кредит🔥Выгодный трейд-ин🔥Скидки на все автомобили от розничной цены🔥Звонить по тел.: ☎ {{phone_common}}",
        "h1": "Автомобили BELGEE X70 Обновленный в Пензе"
    },
    "/models/x70/": {
        "title": "Купить⭐BELGEE X70⭐от {{priceb-belgee-x70}} в Пензе. Цены и комплектации на новые авто в автосалоне официального дилера Белджи🔥",
        "description": "Белджи икс 70 купить в Пензе🔥Выгодный кредит🔥Выгодный трейд-ин🔥Скидки на все автомобили от розничной цены🔥Звонить по тел.: ☎ {{phone_common}}",
        "h1": "Автомобили BELGEE X70 в Пензе"
    },
    "/test-drive/": {
        "title": "Записаться на тест-драйв автомобилей Belgee",
        "description": "Записаться на тест-драйв автомобилей Belgee у официального дилера ПАРТНЕР АВТО ПЕНЗА",
        "h1": "Записаться на тест-драйв"
    }
}