[
  {
    "id": "baic-u5_plus",
    "model": "BAIC U5 PLUS",
    "price": "1515000",
    "benefit": "530000",
    "link": "/models/u5_plus/"
  },
  {
    "id": "baic-u5_plus-cng",
    "model": "BAIC U5 PLUS CNG",
    "price": 1485000,
    "benefit": 0,
    "link": "/models/u5_plus-cng/"
  },
  {
    "id": "baic-x35",
    "model": "BAIC X35",
    "price": "1355000",
    "benefit": "845000",
    "link": "/models/x35/"
  },
  {
    "id": "baic-x55",
    "model": "BAIC X55",
    "price": "2150000",
    "benefit": "1100000",
    "link": "/models/x55/"
  },
  {
    "id": "baic-x7",
    "model": "BAIC X7",
    "price": "1990000",
    "benefit": "900000",
    "link": "/models/x7/"
  },
  {
    "id": "baic-x75",
    "model": "BAIC X75",
    "price": "2290000",
    "benefit": "700000",
    "link": "/models/x75/"
  },
  {
    "id": "baic-bj40",
    "model": "BAIC BJ40",
    "price": 3650000,
    "benefit": 0,
    "link": "/models/bj40/"
  }
]