[
  {
    "id": "tank-300",
    "brand": "tank",
    "model": "300",
    "price": "3749000",
    "benefit": "",
    "link": "https://tank.ru/models/tank-300"
  },
  {
    "id": "tank-400",
    "brand": "tank",
    "model": "400",
    "price": "4749000",
    "benefit": "",
    "link": "https://tank.ru/models/tank-400"
  },
  {
    "id": "tank-500",
    "brand": "tank",
    "model": "500",
    "price": "5999000",
    "benefit": "",
    "link": "https://tank.ru/models/tank-500"
  },
  {
    "id": "tank-700",
    "brand": "tank",
    "model": "700",
    "price": "7999000",
    "benefit": "",
    "link": "https://tank.ru/models/tank-700"
  }
]