[
    {
        "mark_id": "JAECOO",
        "id": "j7",
        "show": true,
        "homeImg": "/img/model-bg.webp",
        "slogan": "Следуй за открытиями",
        "name": "J7",
        "price": 3649000,
        "benefit": 450000,
        "benefits": [
            {
                "url": "#common-modal",
                "label": "Выгодный трейд-ин",
                "icon_name": "mdi:credit-card-check-outline",
                "data_title": "Выгодный трейд-ин",
                "data_form_name": "Выгодный трейд-ин. JAECOO J7",
                "view": "popup-link"
            },
            {
                "url": "#common-modal",
                "label": "Выгодный кредит",
                "icon_name": "mdi:gift-outline",
                "data_title": "Выгодный кредит",
                "data_form_name": "Выгодный кредит. JAECOO J7",
                "view": "popup-link"
            }
        ],
        "thumb": "https://tank.ru/uploads/car_variant_color_sequence/defc347ca8d1a334116ca45277d5a6dd.png",
        "colors": [
            {
                "id": "red",
                "name": "Красный Эльтон, металлик",
                "carImage": "https://tank.ru/uploads/car_variant_color_sequence/5a4450455f9de0c0f3dd6fd6aa029ae7.png",
                "style": "background-color: #ef2929;"
            },
            {
                "id": "orange",
                "name": "Чарский Оранжевый, металлик",
                "carImage": "https://tank.ru/uploads/car_variant_color_sequence/61aab46d6fccaf0d2a047925cf8f0684.png",
                "style": "background-color: #df4c30;"
            },
            {
                "id": "gray",
                "name": "Серый Шантар",
                "carImage": "https://tank.ru/uploads/car_variant_color_sequence/db5a358aa9c6471a4f23ffd84270da78.png",
                "style": "background-color: #c6c9ce;"
            },
            {
                "id": "black",
                "name": "Черный Богдо, металлик",
                "carImage": "https://tank.ru/uploads/car_variant_color_sequence/2c18b43a8d5223f07af8e4dcace56b77.png",
                "style": "background-color: #212329;"
            },
            {
                "id": "white",
                "name": "Белый Ольхон, металлик",
                "carImage": "https://tank.ru/uploads/car_variant_color_sequence/0d372feb159f387bec68136ee77e6058.png",
                "style": "background-color: #e6e7e8;"
            }
        ],
        "feed_names": [
        ],
        "photos": "",
        "chars": {
            "seats": "5 мест",
            "fuel": "Бензин",
            "gearbox": "8AT"
        },
        "globalChars": [
            {
                "id": "wheelbase",
                "title": "Колёсная база",
                "value": "2750",
                "measure": "мм"
            },
            {
                "id": "length",
                "title": "Длина",
                "value": "4760",
                "measure": "мм"
            },
            {
                "id": "width",
                "title": "Ширина",
                "value": "1930",
                "measure": "мм"
            },
            {
                "id": "engine",
                "title": "Объем двигателя",
                "value": "2.0",
                "measure": "л."
            },
            {
                "id": "torque",
                "title": "Крутящий момент",
                "value": "380",
                "measure": "н.м."
            },
            {
                "id": "transmission",
                "title": "Привод",
                "value": "Полный",
                "measure": ""
            }
        ]
    },
    {
        "mark_id": "JAECOO",
        "id": "j8",
        "show": true,
        "homeImg": "/img/model-bg.webp",
        "slogan": "Следуй за открытиями",
        "name": "J8",
        "price": 3649000,
        "benefit": 450000,
        "benefits": [
            {
                "url": "#common-modal",
                "label": "Выгодный трейд-ин",
                "icon_name": "mdi:credit-card-check-outline",
                "data_title": "Выгодный трейд-ин",
                "data_form_name": "Выгодный трейд-ин. JAECOO J8",
                "view": "popup-link"
            },
            {
                "url": "#common-modal",
                "label": "Выгодный кредит",
                "icon_name": "mdi:gift-outline",
                "data_title": "Выгодный кредит",
                "data_form_name": "Выгодный кредит. JAECOO J8",
                "view": "popup-link"
            }
        ],
        "thumb": "https://tank.ru/uploads/car_variant_color_sequence/defc347ca8d1a334116ca45277d5a6dd.png",
        "colors": [
            {
                "id": "red",
                "name": "Красный Эльтон, металлик",
                "carImage": "https://tank.ru/uploads/car_variant_color_sequence/5a4450455f9de0c0f3dd6fd6aa029ae7.png",
                "style": "background-color: #ef2929;"
            },
            {
                "id": "orange",
                "name": "Чарский Оранжевый, металлик",
                "carImage": "https://tank.ru/uploads/car_variant_color_sequence/61aab46d6fccaf0d2a047925cf8f0684.png",
                "style": "background-color: #df4c30;"
            },
            {
                "id": "gray",
                "name": "Серый Шантар",
                "carImage": "https://tank.ru/uploads/car_variant_color_sequence/db5a358aa9c6471a4f23ffd84270da78.png",
                "style": "background-color: #c6c9ce;"
            },
            {
                "id": "black",
                "name": "Черный Богдо, металлик",
                "carImage": "https://tank.ru/uploads/car_variant_color_sequence/2c18b43a8d5223f07af8e4dcace56b77.png",
                "style": "background-color: #212329;"
            },
            {
                "id": "white",
                "name": "Белый Ольхон, металлик",
                "carImage": "https://tank.ru/uploads/car_variant_color_sequence/0d372feb159f387bec68136ee77e6058.png",
                "style": "background-color: #e6e7e8;"
            }
        ],
        "feed_names": [
        ],
        "photos": "",
        "chars": {
            "seats": "5 мест",
            "fuel": "Бензин",
            "gearbox": "8AT"
        },
        "globalChars": [
            {
                "id": "wheelbase",
                "title": "Колёсная база",
                "value": "2750",
                "measure": "мм"
            },
            {
                "id": "length",
                "title": "Длина",
                "value": "4760",
                "measure": "мм"
            },
            {
                "id": "width",
                "title": "Ширина",
                "value": "1930",
                "measure": "мм"
            },
            {
                "id": "engine",
                "title": "Объем двигателя",
                "value": "2.0",
                "measure": "л."
            },
            {
                "id": "torque",
                "title": "Крутящий момент",
                "value": "380",
                "measure": "н.м."
            },
            {
                "id": "transmission",
                "title": "Привод",
                "value": "Полный",
                "measure": ""
            }
        ]
    },
    {
        "mark_id": "JAECOO",
        "id": "j5",
        "show": true,
        "homeImg": "/img/model-bg.webp",
        "slogan": "Следуй за открытиями",
        "name": "J5",
        "price": 3649000,
        "benefit": 450000,
        "benefits": [
            {
                "url": "#common-modal",
                "label": "Выгодный трейд-ин",
                "icon_name": "mdi:credit-card-check-outline",
                "data_title": "Выгодный трейд-ин",
                "data_form_name": "Выгодный трейд-ин. JAECOO J5",
                "view": "popup-link"
            },
            {
                "url": "#common-modal",
                "label": "Выгодный кредит",
                "icon_name": "mdi:gift-outline",
                "data_title": "Выгодный кредит",
                "data_form_name": "Выгодный кредит. JAECOO J5",
                "view": "popup-link"
            }
        ],
        "thumb": "https://tank.ru/uploads/car_variant_color_sequence/defc347ca8d1a334116ca45277d5a6dd.png",
        "colors": [
            {
                "id": "red",
                "name": "Красный Эльтон, металлик",
                "carImage": "https://tank.ru/uploads/car_variant_color_sequence/5a4450455f9de0c0f3dd6fd6aa029ae7.png",
                "style": "background-color: #ef2929;"
            },
            {
                "id": "orange",
                "name": "Чарский Оранжевый, металлик",
                "carImage": "https://tank.ru/uploads/car_variant_color_sequence/61aab46d6fccaf0d2a047925cf8f0684.png",
                "style": "background-color: #df4c30;"
            },
            {
                "id": "gray",
                "name": "Серый Шантар",
                "carImage": "https://tank.ru/uploads/car_variant_color_sequence/db5a358aa9c6471a4f23ffd84270da78.png",
                "style": "background-color: #c6c9ce;"
            },
            {
                "id": "black",
                "name": "Черный Богдо, металлик",
                "carImage": "https://tank.ru/uploads/car_variant_color_sequence/2c18b43a8d5223f07af8e4dcace56b77.png",
                "style": "background-color: #212329;"
            },
            {
                "id": "white",
                "name": "Белый Ольхон, металлик",
                "carImage": "https://tank.ru/uploads/car_variant_color_sequence/0d372feb159f387bec68136ee77e6058.png",
                "style": "background-color: #e6e7e8;"
            }
        ],
        "feed_names": [
        ],
        "photos": "",
        "chars": {
            "seats": "5 мест",
            "fuel": "Бензин",
            "gearbox": "8AT"
        },
        "globalChars": [
            {
                "id": "wheelbase",
                "title": "Колёсная база",
                "value": "2750",
                "measure": "мм"
            },
            {
                "id": "length",
                "title": "Длина",
                "value": "4760",
                "measure": "мм"
            },
            {
                "id": "width",
                "title": "Ширина",
                "value": "1930",
                "measure": "мм"
            },
            {
                "id": "engine",
                "title": "Объем двигателя",
                "value": "2.0",
                "measure": "л."
            },
            {
                "id": "torque",
                "title": "Крутящий момент",
                "value": "380",
                "measure": "н.м."
            },
            {
                "id": "transmission",
                "title": "Привод",
                "value": "Полный",
                "measure": ""
            }
        ]
    }
]