[
    {
        "id": 1,
        "show": true,
        "type": "",
        "view": "popup-link",
        "videoUrl": "",
        "imageUrl": "/img/banners/work-hours.webp",
        "title": "График работы ДЦ в новогодние праздники:",
        "descr": "30.12 – с 08-00 до 18-00 <br/><span class='text-red-500'>31.12 – 02.01, 07.01 – выходной</span> <br/>03.01 – 06.01 – с 09-00 до 17-00 <br/>08.01 – с 09-00 до 17-00",
        "alt": "График работы",
        "btn": "",
        "btnUrl": "#common-modal",
        "dataTitle": "",
        "dataFormName": "",
        "badge": "",
        "autoplay": 10000
    },
    {
        "id": 2,
        "show": true,
        "type": "",
        "view": "popup-link",
        "videoUrl": "",
        "imageUrl": "/img/banners/bj40.webp",
        "title": "<span class='text-xl sm:text-4xl md:text-5xl lg:text-6xl font-bold uppercase'>0%</span> первый взнос",
        "descr": "",
        "alt": "0% первый взнос",
        "btn": "Узнать подробнее",
        "btnUrl": "#common-modal",
        "dataTitle": "Узнать подробнее",
        "dataFormName": "Узнать подробнее. 0% первый взнос. Баннер",
        "badge": "",
        "autoplay": 5000
    }
]