[
    {
        "id": 0,
        "show": true,
        "type": "special",
        "view": "link",
        "videoUrl": "",
        "imageUrl": "https://cdn.alexsab.ru/specials/belgee/belgee-orenburg/special-offer/special-offer-1920x1080.webp",
        "mobileImageUrl": "https://cdn.alexsab.ru/specials/belgee/belgee-orenburg/special-offer/special-offer-640x900.webp",
        "title": "",
        "descr": "",
        "btn": "",
        "bannerUrl": "/special-offers/special-offer/",
        "gradient": false,
        "dataTitle": "",
        "dataFormName": "",
        "autoplay": 6000
    },
    {
        "id": 0,
        "show": true,
        "type": "",
        "view": "link",
        "videoUrl": "",
        "imageUrl": "https://cdn.alexsab.ru/specials/belgee/rassrochka/rassrochka-1920x1080-notxt.webp",
        "mobileImageUrl": "https://cdn.alexsab.ru/specials/belgee/rassrochka/rassrochka-640x800-notxt.webp",
        "title": "До конца месяца",
        "descr": "СТАВКА от <b>0,01%</b><br>ПЕРВОНАЧАЛЬНЫЙ ВЗНОС от <b>40%</b><br>СРОК от <b>12</b> до <b>96</b> месяцев",
        "btn": "Подробнее",
        "btnUrl": "/special-offers/rassrochka/",
        "dataTitle": "Ставка 0.01%, Первоначальный взнос 40%, Срок 12-96 месяцев",
        "dataFormName": "Подробнее. Ставка 0.01%, Первоначальный взнос 40%, Срок 12-96 месяцев. Баннер",
        "badge": {
            "autoname": "",
            "title": "",
            "descr": "ПАО \"Альфабанк\". Не является публичной офертой.",
            "image": "",
            "position": "left"
        },
        "autoplay": 6000
    },
    {
        "id": 0,
        "show": false,
        "type": "",
        "view": "link",
        "videoUrl": "",
        "imageUrl": "https://cdn.alexsab.ru/specials/belgee/zimnie-shiny-v-podarok/belgee-winter-tires-1920x1080-notext.webp",
        "title": "Зимние шины в подарок",
        "descr": "На весь модельный ряд в Belgee Партнер-Авто",
        "btn": "Подробнее",
        "btnUrl": "/special-offers/zimnie-shiny-v-podarok/",
        "dataTitle": "",
        "dataFormName": "",
        "badge": {
            "autoname": "",
            "title": "",
            "descr": "",
            "image": "https://cdn.alexsab.ru/specials/belgee/zimnie-shiny-v-podarok/belgee-winter-tires-icon.webp",
            "position": "left"
        },
        "autoplay": 6000
    },
    {
        "id": 0,
        "show": true,
        "type": "",
        "view": "popup-link",
        "videoUrl": "",
        "imageUrl": "https://cdn.alexsab.ru/main-sliders/belgee/kzy9h57l5mnwibbxeuyzekpa0yzhzh481.webp",
        "title": "Выгодное предложение на BELGEE X50",
        "descr": "Успей забронировать свой Белджи",
        "btn": "Подробнее",
        "btnUrl": "#common-modal",
        "dataTitle": "Выгодное предложение на BELGEE X50",
        "dataFormName": "Подробнее. Выгодное предложение на BELGEE X50. Баннер",
        "badge": "",
        "autoplay": 6000
    },
    {
        "id": 1,
        "show": true,
        "type": "",
        "view": "popup-link",
        "videoUrl": "",
        "imageUrl": "https://cdn.alexsab.ru/main-sliders/belgee/m0xzboh90uxd7yarz4xl19zaczawu1v61.webp",
        "title": "Новый BELGEE X70",
        "descr": "Уже в продаже!",
        "btn": "Подробнее",
        "btnUrl": "#common-modal",
        "dataTitle": "Новый BELGEE X70",
        "dataFormName": "Подробнее. Новый BELGEE X70. Баннер",
        "badge": "",
        "autoplay": 6000
    }
]